ACKNOWLEDGE.txt
CHANGELOG.txt
LICENSE.txt
MANIFEST.in
README.txt
distribute_setup.py
setup.py
yarest_ui.py
examples/extender.py
examples/profiles-posix.ini
examples/profiles-windows-rdp.ini
examples/profiles-windows-tightvnc-1.3.ini
examples/profiles-windows-tightvnc-2.x.ini
examples/profiles-windows-ultravnc.ini
examples/tightvnc-2.x.reg
examples/ultravnc.ini
installers/windows/README.txt
installers/windows/logo.ico
installers/windows/x86.nsh
installers/windows/yarest-x86.nsi
installers/windows/includes/EnvVarUpdate.nsh
installers/windows/includes/descriptions.nsh
installers/windows/includes/functions.nsh
installers/windows/includes/languages.nsh
installers/windows/includes/pages.nsh
installers/windows/includes/sections.nsh
installers/windows/scripts/checkforpycrypto.py
installers/windows/scripts/checkforwxpython.py
installers/windows/scripts/getpythondir.py
resources/README.txt
resources/embed_docs.py
resources/embed_images.py
resources/logo-128x128.png
resources/logo-16x16.png
resources/logo-256x256.png
resources/logo-32x32.png
resources/logo-512x512.png
resources/logo-64x64.png
yarest/__init__.py
yarest/_constants.py
yarest/_exceptions.py
yarest/_messages.py
yarest/_profiles.py
yarest/_ssh.py
yarest/_support.py
yarest.egg-info/PKG-INFO
yarest.egg-info/SOURCES.txt
yarest.egg-info/dependency_links.txt
yarest.egg-info/entry_points.txt
yarest.egg-info/not-zip-safe
yarest.egg-info/requires.txt
yarest.egg-info/top_level.txt
yarest/gui/__init__.py
yarest/gui/_about.py
yarest/gui/_constants.py
yarest/gui/_docs.py
yarest/gui/_edit.py
yarest/gui/_images.py
yarest/gui/_main.py
yarest/gui/_messages.py
yarest/gui/_run.py