Metadata-Version: 1.0
Name: yarest
Version: 0.5.0
Summary: Yet Another REmote Support Tool
Home-page: http://code.google.com/p/yarest/
Author: Mike Fled
Author-email: nonvenia@gmail.com
License: MIT
Platform: Posix; MacOS X; Windows
Classifier: Development Status :: 4 - Beta
Classifier: Intended Audience :: Information Technology
Classifier: Intended Audience :: Developers
Classifier: License :: OSI Approved :: MIT License
Classifier: Operating System :: OS Independent
Classifier: Programming Language :: Python :: 2.6
Classifier: Programming Language :: Python :: 2.7
Classifier: Topic :: Internet
Classifier: Topic :: Security
Classifier: Topic :: System :: Networking
